aiokit/__init__.py
aiokit/_aiothing.py
aiokit/_executors.py
aiokit/_utils.py
aiokit-1.3.7.dist-info/METADATA
aiokit-1.3.7.dist-info/WHEEL
aiokit-1.3.7.dist-info/entry_points.txt
aiokit-1.3.7.dist-info/RECORD
